{
  "PackageData": [
    {
      "Row": [
        {
          "SchemaColumnUId": "ae0e45ca-c495-4fe7-a39d-3ab7278e1617",
          "ColumnName": "Id",
          "Value": "078d5c14-bf0b-4493-b51e-16641ba1f14a"
        },
        {
          "SchemaColumnUId": "009571ab-9c5d-4a20-bf83-dd499ed5a833",
          "ColumnName": "Description",
          "Value": ""
        },
        {
          "SchemaColumnUId": "547bff8d-f717-4316-846c-3ff1f0e36e6e",
          "ColumnName": "Name",
          "Value": "Income or expense type"
        }
      ]
    },
    {
      "Row": [
        {
          "SchemaColumnUId": "ae0e45ca-c495-4fe7-a39d-3ab7278e1617",
          "ColumnName": "Id",
          "Value": "0821262e-99fb-4966-aa1e-40805fad7438"
        },
        {
          "SchemaColumnUId": "009571ab-9c5d-4a20-bf83-dd499ed5a833",
          "ColumnName": "Description",
          "Value": ""
        },
        {
          "SchemaColumnUId": "547bff8d-f717-4316-846c-3ff1f0e36e6e",
          "ColumnName": "Name",
          "Value": "Document in package"
        }
      ]
    },
    {
      "Row": [
        {
          "SchemaColumnUId": "ae0e45ca-c495-4fe7-a39d-3ab7278e1617",
          "ColumnName": "Id",
          "Value": "11345677-50c0-456c-a244-42e46856bcb6"
        },
        {
          "SchemaColumnUId": "009571ab-9c5d-4a20-bf83-dd499ed5a833",
          "ColumnName": "Description",
          "Value": ""
        },
        {
          "SchemaColumnUId": "547bff8d-f717-4316-846c-3ff1f0e36e6e",
          "ColumnName": "Name",
          "Value": "District"
        }
      ]
    },
    {
      "Row": [
        {
          "SchemaColumnUId": "ae0e45ca-c495-4fe7-a39d-3ab7278e1617",
          "ColumnName": "Id",
          "Value": "1a7af011-23ed-41f5-aa80-6ca77e11bf8f"
        },
        {
          "SchemaColumnUId": "009571ab-9c5d-4a20-bf83-dd499ed5a833",
          "ColumnName": "Description",
          "Value": ""
        },
        {
          "SchemaColumnUId": "547bff8d-f717-4316-846c-3ff1f0e36e6e",
          "ColumnName": "Name",
          "Value": "Loan Status"
        }
      ]
    },
    {
      "Row": [
        {
          "SchemaColumnUId": "ae0e45ca-c495-4fe7-a39d-3ab7278e1617",
          "ColumnName": "Id",
          "Value": "1f3fad11-af20-40ac-b164-16ca8132dfb0"
        },
        {
          "SchemaColumnUId": "009571ab-9c5d-4a20-bf83-dd499ed5a833",
          "ColumnName": "Description",
          "Value": ""
        },
        {
          "SchemaColumnUId": "547bff8d-f717-4316-846c-3ff1f0e36e6e",
          "ColumnName": "Name",
          "Value": "Income and expenses source"
        }
      ]
    },
    {
      "Row": [
        {
          "SchemaColumnUId": "ae0e45ca-c495-4fe7-a39d-3ab7278e1617",
          "ColumnName": "Id",
          "Value": "1f472ca7-5726-4af8-8a4d-83b1cf0a2d78"
        },
        {
          "SchemaColumnUId": "009571ab-9c5d-4a20-bf83-dd499ed5a833",
          "ColumnName": "Description",
          "Value": ""
        },
        {
          "SchemaColumnUId": "547bff8d-f717-4316-846c-3ff1f0e36e6e",
          "ColumnName": "Name",
          "Value": "Documents package"
        }
      ]
    },
    {
      "Row": [
        {
          "SchemaColumnUId": "ae0e45ca-c495-4fe7-a39d-3ab7278e1617",
          "ColumnName": "Id",
          "Value": "2b016fe0-67f0-48c0-8dd3-22e5f9cbb311"
        },
        {
          "SchemaColumnUId": "009571ab-9c5d-4a20-bf83-dd499ed5a833",
          "ColumnName": "Description",
          "Value": ""
        },
        {
          "SchemaColumnUId": "547bff8d-f717-4316-846c-3ff1f0e36e6e",
          "ColumnName": "Name",
          "Value": "Sub Sector"
        }
      ]
    },
    {
      "Row": [
        {
          "SchemaColumnUId": "ae0e45ca-c495-4fe7-a39d-3ab7278e1617",
          "ColumnName": "Id",
          "Value": "3d7b541e-2bce-4635-b98a-2f011d1947c2"
        },
        {
          "SchemaColumnUId": "009571ab-9c5d-4a20-bf83-dd499ed5a833",
          "ColumnName": "Description",
          "Value": ""
        },
        {
          "SchemaColumnUId": "547bff8d-f717-4316-846c-3ff1f0e36e6e",
          "ColumnName": "Name",
          "Value": "Application parameters"
        }
      ]
    },
    {
      "Row": [
        {
          "SchemaColumnUId": "ae0e45ca-c495-4fe7-a39d-3ab7278e1617",
          "ColumnName": "Id",
          "Value": "4491d59a-b789-44ea-a526-44eecd04f8b6"
        },
        {
          "SchemaColumnUId": "009571ab-9c5d-4a20-bf83-dd499ed5a833",
          "ColumnName": "Description",
          "Value": ""
        },
        {
          "SchemaColumnUId": "547bff8d-f717-4316-846c-3ff1f0e36e6e",
          "ColumnName": "Name",
          "Value": "Document Upload Status"
        }
      ]
    },
    {
      "Row": [
        {
          "SchemaColumnUId": "ae0e45ca-c495-4fe7-a39d-3ab7278e1617",
          "ColumnName": "Id",
          "Value": "73037155-840d-44b9-95f7-548f8d7110ad"
        },
        {
          "SchemaColumnUId": "009571ab-9c5d-4a20-bf83-dd499ed5a833",
          "ColumnName": "Description",
          "Value": ""
        },
        {
          "SchemaColumnUId": "547bff8d-f717-4316-846c-3ff1f0e36e6e",
          "ColumnName": "Name",
          "Value": "Registration document group"
        }
      ]
    },
    {
      "Row": [
        {
          "SchemaColumnUId": "ae0e45ca-c495-4fe7-a39d-3ab7278e1617",
          "ColumnName": "Id",
          "Value": "830d7c2a-b559-4a9a-9b12-e59c73e76aea"
        },
        {
          "SchemaColumnUId": "009571ab-9c5d-4a20-bf83-dd499ed5a833",
          "ColumnName": "Description",
          "Value": ""
        },
        {
          "SchemaColumnUId": "547bff8d-f717-4316-846c-3ff1f0e36e6e",
          "ColumnName": "Name",
          "Value": "Parameter classification in product condition"
        }
      ]
    },
    {
      "Row": [
        {
          "SchemaColumnUId": "ae0e45ca-c495-4fe7-a39d-3ab7278e1617",
          "ColumnName": "Id",
          "Value": "8d37e3ca-53d6-4941-8364-a994c1890235"
        },
        {
          "SchemaColumnUId": "009571ab-9c5d-4a20-bf83-dd499ed5a833",
          "ColumnName": "Description",
          "Value": ""
        },
        {
          "SchemaColumnUId": "547bff8d-f717-4316-846c-3ff1f0e36e6e",
          "ColumnName": "Name",
          "Value": "Package in installed application"
        }
      ]
    },
    {
      "Row": [
        {
          "SchemaColumnUId": "ae0e45ca-c495-4fe7-a39d-3ab7278e1617",
          "ColumnName": "Id",
          "Value": "92d4fe4a-4f9d-4c32-babc-bc7c0b98e55e"
        },
        {
          "SchemaColumnUId": "009571ab-9c5d-4a20-bf83-dd499ed5a833",
          "ColumnName": "Description",
          "Value": ""
        },
        {
          "SchemaColumnUId": "547bff8d-f717-4316-846c-3ff1f0e36e6e",
          "ColumnName": "Name",
          "Value": "Client type for product"
        }
      ]
    },
    {
      "Row": [
        {
          "SchemaColumnUId": "ae0e45ca-c495-4fe7-a39d-3ab7278e1617",
          "ColumnName": "Id",
          "Value": "b6053e00-4eb4-4add-b186-b85c0e3a6cdf"
        },
        {
          "SchemaColumnUId": "009571ab-9c5d-4a20-bf83-dd499ed5a833",
          "ColumnName": "Description",
          "Value": ""
        },
        {
          "SchemaColumnUId": "547bff8d-f717-4316-846c-3ff1f0e36e6e",
          "ColumnName": "Name",
          "Value": "Product Sector"
        }
      ]
    },
    {
      "Row": [
        {
          "SchemaColumnUId": "ae0e45ca-c495-4fe7-a39d-3ab7278e1617",
          "ColumnName": "Id",
          "Value": "b67ddb94-ac97-4bf9-bb2d-b655ca65bb93"
        },
        {
          "SchemaColumnUId": "009571ab-9c5d-4a20-bf83-dd499ed5a833",
          "ColumnName": "Description",
          "Value": ""
        },
        {
          "SchemaColumnUId": "547bff8d-f717-4316-846c-3ff1f0e36e6e",
          "ColumnName": "Name",
          "Value": "Financial Type"
        }
      ]
    },
    {
      "Row": [
        {
          "SchemaColumnUId": "ae0e45ca-c495-4fe7-a39d-3ab7278e1617",
          "ColumnName": "Id",
          "Value": "b8ca026b-d5b3-47bc-bc80-5b2ad640a2e8"
        },
        {
          "SchemaColumnUId": "009571ab-9c5d-4a20-bf83-dd499ed5a833",
          "ColumnName": "Description",
          "Value": ""
        },
        {
          "SchemaColumnUId": "547bff8d-f717-4316-846c-3ff1f0e36e6e",
          "ColumnName": "Name",
          "Value": "Opportunity condition"
        }
      ]
    },
    {
      "Row": [
        {
          "SchemaColumnUId": "ae0e45ca-c495-4fe7-a39d-3ab7278e1617",
          "ColumnName": "Id",
          "Value": "c642e994-c2d1-4385-9f29-72c17e80cea2"
        },
        {
          "SchemaColumnUId": "009571ab-9c5d-4a20-bf83-dd499ed5a833",
          "ColumnName": "Description",
          "Value": ""
        },
        {
          "SchemaColumnUId": "547bff8d-f717-4316-846c-3ff1f0e36e6e",
          "ColumnName": "Name",
          "Value": "Financial Category"
        }
      ]
    },
    {
      "Row": [
        {
          "SchemaColumnUId": "ae0e45ca-c495-4fe7-a39d-3ab7278e1617",
          "ColumnName": "Id",
          "Value": "cd26574d-3663-4573-adab-8334e8e05101"
        },
        {
          "SchemaColumnUId": "009571ab-9c5d-4a20-bf83-dd499ed5a833",
          "ColumnName": "Description",
          "Value": ""
        },
        {
          "SchemaColumnUId": "547bff8d-f717-4316-846c-3ff1f0e36e6e",
          "ColumnName": "Name",
          "Value": "Sector"
        }
      ]
    },
    {
      "Row": [
        {
          "SchemaColumnUId": "ae0e45ca-c495-4fe7-a39d-3ab7278e1617",
          "ColumnName": "Id",
          "Value": "d5918b95-7a54-41f1-a0f8-6a9275b65d47"
        },
        {
          "SchemaColumnUId": "009571ab-9c5d-4a20-bf83-dd499ed5a833",
          "ColumnName": "Description",
          "Value": ""
        },
        {
          "SchemaColumnUId": "547bff8d-f717-4316-846c-3ff1f0e36e6e",
          "ColumnName": "Name",
          "Value": "Parameter in product condition"
        }
      ]
    },
    {
      "Row": [
        {
          "SchemaColumnUId": "ae0e45ca-c495-4fe7-a39d-3ab7278e1617",
          "ColumnName": "Id",
          "Value": "d5c090d4-8fe4-45d0-a523-ae6c11885f3e"
        },
        {
          "SchemaColumnUId": "009571ab-9c5d-4a20-bf83-dd499ed5a833",
          "ColumnName": "Description",
          "Value": ""
        },
        {
          "SchemaColumnUId": "547bff8d-f717-4316-846c-3ff1f0e36e6e",
          "ColumnName": "Name",
          "Value": "Location Type"
        }
      ]
    },
    {
      "Row": [
        {
          "SchemaColumnUId": "ae0e45ca-c495-4fe7-a39d-3ab7278e1617",
          "ColumnName": "Id",
          "Value": "e43577bb-9705-447a-a39a-8d2ab4a95b0c"
        },
        {
          "SchemaColumnUId": "009571ab-9c5d-4a20-bf83-dd499ed5a833",
          "ColumnName": "Description",
          "Value": ""
        },
        {
          "SchemaColumnUId": "547bff8d-f717-4316-846c-3ff1f0e36e6e",
          "ColumnName": "Name",
          "Value": "Town/Village"
        }
      ]
    },
    {
      "Row": [
        {
          "SchemaColumnUId": "ae0e45ca-c495-4fe7-a39d-3ab7278e1617",
          "ColumnName": "Id",
          "Value": "e90bb562-32b2-4a1c-b530-dce30b53dfa2"
        },
        {
          "SchemaColumnUId": "009571ab-9c5d-4a20-bf83-dd499ed5a833",
          "ColumnName": "Description",
          "Value": ""
        },
        {
          "SchemaColumnUId": "547bff8d-f717-4316-846c-3ff1f0e36e6e",
          "ColumnName": "Name",
          "Value": "Identity document"
        }
      ]
    }
  ]
}